LICENSE
setup.cfg
setup.py
geppy/__init__.py
geppy.egg-info/PKG-INFO
geppy.egg-info/SOURCES.txt
geppy.egg-info/dependency_links.txt
geppy.egg-info/requires.txt
geppy.egg-info/top_level.txt
geppy/algorithms/__init__.py
geppy/algorithms/basic.py
geppy/algorithms/copt.py
geppy/core/__init__.py
geppy/core/entity.py
geppy/core/symbol.py
geppy/support/__init__.py
geppy/support/simplification.py
geppy/support/visualization.py
geppy/tools/__init__.py
geppy/tools/_util.py
geppy/tools/crossover.py
geppy/tools/generator.py
geppy/tools/mutation.py
geppy/tools/parser.py
geppy/tools/toolbox.py