Metadata-Version: 2.1
Name: geppy
Version: 0.1.3
Summary: A package for gene expression programming in Python.
Home-page: https://github.com/ShuhuaGao/geppy
Author: Shuhua Gao
Author-email: nus.gao.shuhua@gmail.com
License: LGPL-3.0 License
Download-URL: https://github.com/ShuhuaGao/geppy/archive/v0.1.3.tar.gz
Keywords: evolutionary computation,gene expression programming,computational intelligence,genetic programming
Platform: UNKNOWN
Classifier: Programming Language :: Python :: 3.6
Classifier: Programming Language :: Python :: 3.7
Classifier: Programming Language :: Python :: 3.8
Classifier: Programming Language :: Python :: 3.9
Classifier: License :: OSI Approved :: GNU Lesser General Public License v3 (LGPLv3)
Classifier: Operating System :: OS Independent
Classifier: Intended Audience :: Science/Research
Classifier: Topic :: Scientific/Engineering :: Artificial Intelligence
License-File: LICENSE
